autopurple/__init__.py
autopurple/config.py
autopurple/logging.py
autopurple/adapters/__init__.py
autopurple/adapters/pacu_adapter.py
autopurple/adapters/scoutsuite_adapter.py
autopurple/adapters/mcp/__init__.py
autopurple/adapters/mcp/ccapi_client.py
autopurple/adapters/mcp/cfn_client.py
autopurple/adapters/mcp/docs_client.py
autopurple/adapters/mcp/manager.py
autopurple/adapters/mcp/stdio_client.py
autopurple/cli/__init__.py
autopurple/cli/install.py
autopurple/cli/main.py
autopurple/cli/setup.py
autopurple/cli/commands/__init__.py
autopurple/cli/commands/setup.py
autopurple/db/__init__.py
autopurple/db/connection.py
autopurple/db/schema.sql
autopurple/models/__init__.py
autopurple/models/findings.py
autopurple/models/remediation.py
autopurple/models/runs.py
autopurple/models/validations.py
autopurple/orchestrator/__init__.py
autopurple/orchestrator/pipeline.py
autopurple/orchestrator/planner.py
autopurple/orchestrator/validators.py
autopurple-1.2.0.dist-info/METADATA
autopurple-1.2.0.dist-info/WHEEL
autopurple-1.2.0.dist-info/entry_points.txt
autopurple-1.2.0.dist-info/licenses/LICENSE
autopurple-1.2.0.dist-info/RECORD
