Metadata-Version: 2.4
Name: autopurple
Version: 1.2.0
Summary: Claude-powered AWS security automation: discover vulnerabilities with ScoutSuite, validate with Pacu, and remediate via AWS MCP servers
Project-URL: Homepage, https://github.com/autopurple/autopurple
Project-URL: Repository, https://github.com/autopurple/autopurple
Project-URL: Documentation, https://autopurple.readthedocs.io
Project-URL: Issues, https://github.com/autopurple/autopurple/issues
Author-email: AutoPurple Team <team@autopurple.dev>
License: MIT
License-File: LICENSE
Keywords: automation,aws,mcp,pacu,scoutsuite,security
Classifier: Development Status :: 5 - Production/Stable
Classifier: Environment :: Console
Classifier: Intended Audience :: Information Technology
Classifier: Intended Audience :: System Administrators
Classifier: License :: OSI Approved :: MIT License
Classifier: Operating System :: OS Independent
Classifier: Programming Language :: Python :: 3
Classifier: Programming Language :: Python :: 3.11
Classifier: Programming Language :: Python :: 3.12
Classifier: Topic :: Internet :: WWW/HTTP :: HTTP Servers
Classifier: Topic :: Security
Classifier: Topic :: System :: Systems Administration
Requires-Python: >=3.11
Requires-Dist: aiohttp>=3.9.0
Requires-Dist: aiosqlite>=0.19.0
Requires-Dist: anthropic>=0.7.0
Requires-Dist: anyio>=4.2.0
Requires-Dist: boto3>=1.34.0
Requires-Dist: botocore>=1.34.0
Requires-Dist: click>=8.1.0
Requires-Dist: dataclasses-json>=0.6.3
Requires-Dist: netaddr>=0.8.0
Requires-Dist: pydantic-settings>=2.1.0
Requires-Dist: pydantic>=2.5.0
Requires-Dist: python-dateutil>=2.8.0
Requires-Dist: pyyaml>=6.0
Requires-Dist: rich>=13.7.0
Requires-Dist: scoutsuite>=5.14.0
Requires-Dist: sqlalchemy[asyncio]<2.0.0,>=1.3.0
Requires-Dist: sqlite-utils>=3.35.0
Requires-Dist: structlog>=23.2.0
Requires-Dist: tenacity>=8.2.0
Requires-Dist: typer>=0.9.0
Requires-Dist: uv>=0.4.0
Provides-Extra: ai
Requires-Dist: openai>=1.3.0; extra == 'ai'
Provides-Extra: all
Requires-Dist: aws-cdk-lib>=2.100.0; extra == 'all'
Requires-Dist: moto>=4.2.0; extra == 'all'
Requires-Dist: openai>=1.3.0; extra == 'all'
Requires-Dist: pacu>=1.6.1; extra == 'all'
Provides-Extra: aws
Requires-Dist: aws-cdk-lib>=2.100.0; extra == 'aws'
Requires-Dist: moto>=4.2.0; extra == 'aws'
Provides-Extra: dev
Requires-Dist: black>=23.0.0; extra == 'dev'
Requires-Dist: mypy>=1.7.0; extra == 'dev'
Requires-Dist: pre-commit>=3.5.0; extra == 'dev'
Requires-Dist: pytest-asyncio>=0.21.0; extra == 'dev'
Requires-Dist: pytest-cov>=4.1.0; extra == 'dev'
Requires-Dist: pytest>=7.4.0; extra == 'dev'
Requires-Dist: ruff>=0.1.0; extra == 'dev'
Requires-Dist: types-requests>=2.31.0; extra == 'dev'
Provides-Extra: validation
Requires-Dist: pacu>=1.6.1; extra == 'validation'
